Metadata-Version: 2.1
Name: simple-wikiparser
Version: 0.0.0
Summary: A simple Wikipedia parser
Home-page: https://github.com/biswajit2903/SimpleWikiParser
Author: Biswajit Satapathy
Author-email: biswajit2902@gmail.com
License: Apache License 2.0
Classifier: License :: OSI Approved :: Apache Software License
Classifier: Programming Language :: Python :: 3
Classifier: Programming Language :: Python :: 3.8
Classifier: Programming Language :: Python :: 3.9
Classifier: Programming Language :: Python :: 3.10
Requires-Python: >=3.8
License-File: LICENSE
